config/__init__.py
config/endpoints.py
hellomoon/__init__.py
hellomoon/nft.py
hellomoon/nft_summary.py
helpers/__init__.py
helpers/utility.py
hellomoon-0.0.2.dist-info/LICENSE
hellomoon-0.0.2.dist-info/METADATA
hellomoon-0.0.2.dist-info/WHEEL
hellomoon-0.0.2.dist-info/top_level.txt
hellomoon-0.0.2.dist-info/RECORD
