Metadata-Version: 2.1
Name: hellomoon
Version: 0.0.2
Summary: Python SDK for interacting with the Official Hello Moon APIs - https://hellomoon.readme.io/reference/get-your-api-key
Home-page: https://github.com/vmpyre/hellomoon_sdk
Author: vmpyre.sol#0001 (Discord)
Author-email: vmpyrestax@gmail.com
Project-URL: Bug Tracker, https://github.com/vmpyre/hellomoon_sdk/issues
Classifier: Programming Language :: Python :: 3
Classifier: License :: OSI Approved :: MIT License
Classifier: Operating System :: OS Independent
Requires-Python: >=3.8
License-File: LICENSE
